ihide/__init__.py
ihide/_version.py
ihide-1.0.0.data/data/share/jupyter/labextensions/ihide/build_log.json
ihide-1.0.0.data/data/share/jupyter/labextensions/ihide/package.json
ihide-1.0.0.data/data/share/jupyter/labextensions/ihide/static/lib_index_js.5a158fc134045726682f.js
ihide-1.0.0.data/data/share/jupyter/labextensions/ihide/static/lib_index_js.5a158fc134045726682f.js.map
ihide-1.0.0.data/data/share/jupyter/labextensions/ihide/static/remoteEntry.b954ceb735e297733a58.js
ihide-1.0.0.data/data/share/jupyter/labextensions/ihide/static/remoteEntry.b954ceb735e297733a58.js.map
ihide-1.0.0.data/data/share/jupyter/labextensions/ihide/static/style.js
ihide-1.0.0.data/data/share/jupyter/labextensions/ihide/static/style_index_js.8519c0cbd25e9033888a.js
ihide-1.0.0.data/data/share/jupyter/labextensions/ihide/static/style_index_js.8519c0cbd25e9033888a.js.map
ihide-1.0.0.data/data/share/jupyter/labextensions/ihide/install.json
ihide-1.0.0.dist-info/METADATA
ihide-1.0.0.dist-info/WHEEL
ihide-1.0.0.dist-info/licenses/LICENSE
ihide-1.0.0.dist-info/RECORD
